binary_qr_converter/__init__.py
binary_qr_converter/binary_qr.py
binary_qr_converter/converter.py
binary_qr_converter/example.py
binary_qr_converter-0.1.0.dist-info/METADATA
binary_qr_converter-0.1.0.dist-info/WHEEL
binary_qr_converter-0.1.0.dist-info/entry_points.txt
binary_qr_converter-0.1.0.dist-info/top_level.txt
binary_qr_converter-0.1.0.dist-info/RECORD
