Metadata-Version: 2.2
Name: binary-qr-converter
Version: 0.1.0
Summary: Convert binary files to QR codes and back
Home-page: https://github.com/yourusername/binary-qr-converter
Author: Your Name
Author-email: your.email@example.com
Classifier: Programming Language :: Python :: 3
Classifier: License :: OSI Approved :: MIT License
Classifier: Operating System :: OS Independent
Requires-Python: >=3.6
Requires-Dist: qrcode>=7.0
Requires-Dist: pillow>=8.0.0
Requires-Dist: pyzbar>=0.1.8
Dynamic: author
Dynamic: author-email
Dynamic: classifier
Dynamic: description
Dynamic: description-content-type
Dynamic: home-page
Dynamic: requires-dist
Dynamic: requires-python
Dynamic: summary
